RAM/RAM.v
module ram (data_out_1, data_in_1,clk, address_1, write_1,chip_select_1);
parameter ADDRESS_SIZE = 10, DATA_SIZE = 10, MEMORY_SIZE = 1024;
input [ADDRESS_SIZE-1:0] address_1;
input [DATA_SIZE-1:0] data_in_1;
input write_1,write_2, chip_select_1,clk;
output [DATA_SIZE-1:0] data_out_1;
reg [DATA_SIZE-1:0] memory[MEMORY_SIZE-1:0];
integer i;

assign data_out_1 = memory[address_1];


always @(posedge clk) begin
    if (write_1) memory[address_1] = data_in_1; 

end
endmodule

RAM/RAM_test.v
module RAM_test;
reg [9:0] address;
wire [9:0] data_out;
reg [9:0] data_in;
reg write, select,clk,reset;
integer k;
ram RAM (data_out, data_in, clk,address, write, select);
initial begin
    clk=0;
end
always #2 clk = ~clk;

initial begin
	$dumpfile("ram.vcd");
	$dumpvars(0, RAM_test);
end

initial begin
    for (k=0; k<=1023; k=k+1) begin
        address = k;
        data_in = k;  write = 1; select = 1;
        #4 write = 0; select = 0;
    end
    for (k=0; k<=1023; k=k+1) begin
        address = k;
        write = 0; select = 1;
        $display ("Address: %5d, Data: %4d", address,data_out);
        #2 select = 0;
    end
    $finish;
end

endmodule

RAM/ram.vcd
$date
	Wed Jul 28 03:47:48 2021
$end
$version
	Icarus Verilog
$end
$timescale
	1s
$end
$scope module RAM_test $end
$var wire 10 ! data_out [9:0] $end
$var reg 10 " address [9:0] $end
$var reg 1 # clk $end
$var reg 10 $ data_in [9:0] $end
$var reg 1 % select $end
$var reg 1 & write $end
$var integer 32 ' k [31:0] $end
$scope module RAM $end
$var wire 10 ( address_1 [9:0] $end
$var wire 1 % chip_select_1 $end
$var wire 1 # clk $end
$var wire 10 ) data_in_1 [9:0] $end
$var wire 10 * data_out_1 [9:0] $end
$var wire 1 & write_1 $end
$var wire 1 + write_2 $end
$upscope $end
$upscope $end
$enddefinitions $end
#0
$dumpvars
z+
bx *
b0 )
b0 (
b0 '
1&
1%
b0 $
0#
b0 "
bx !
$end
#2
b0 !
b0 *
1#
#4
0#
b1 $
b1 )
bx !
bx *
b1 "
b1 (
b1 '
1%
1&
#6
b1 !
b1 *
1#
#8
0#
b10 $
b10 )
bx !
bx *
b10 "
b10 (
b10 '
1%
1&
#10
b10 !
b10 *
1#
#12
0#
b11 $
b11 )
bx !
bx *
b11 "
b11 (
b11 '
1%
1&
#14
b11 !
b11 *
1#
#16
0#
b100 $
b100 )
bx !
bx *
b100 "
b100 (
b100 '
1%
1&
#18
b100 !
b100 *
1#
#20
0#
b101 $
b101 )
bx !
bx *
b101 "
b101 (
b101 '
1%
1&
#22
b101 !
b101 *
1#
#24
0#
b110 $
b110 )
bx !
bx *
b110 "
b110 (
b110 '
1%
1&
#26
b110 !
b110 *
1#
#28
0#
b111 $
b111 )
bx !
bx *
b111 "
b111 (
b111 '
1%
1&
#30
b111 !
b111 *
1#
#32
0#
b1000 $
b1000 )
bx !
bx *
b1000 "
b1000 (
b1000 '
1%
1&
#34
b1000 !
b1000 *
1#
#36
0#
b1001 $
b1001 )
bx !
bx *
b1001 "
b1001 (
b1001 '
1%
1&
#38
b1001 !
b1001 *
1#
#40
0#
b1010 $
b1010 )
bx !
bx *
b1010 "
b1010 (
b1010 '
1%
1&
#42
b1010 !
b1010 *
1#
#44
0#
b1011 $
b1011 )
bx !
bx *
b1011 "
b1011 (
b1011 '
1%
1&
#46
b1011 !
b1011 *
1#
#48
0#
b1100 $
b1100 )
bx !
bx *
b1100 "
b1100 (
b1100 '
1%
1&
#50
b1100 !
b1100 *
1#
#52
0#
b1101 $
b1101 )
bx !
bx *
b1101 "
b1101 (
b1101 '
1%
1&
#54
b1101 !
b1101 *
1#
#56
0#
b1110 $
b1110 )
bx !
bx *
b1110 "
b1110 (
b1110 '
1%
1&
#58
b1110 !
b1110 *
1#
#60
0#
b1111 $
b1111 )
bx !
bx *
b1111 "
b1111 (
b1111 '
1%
1&
#62
b1111 !
b1111 *
1#
#64
0#
b10000 $
b10000 )
bx !
bx *
b10000 "
b10000 (
b10000 '
1%
1&
#66
b10000 !
b10000 *
1#
#68
0#
b10001 $
b10001 )
bx !
bx *
b10001 "
b10001 (
b10001 '
1%
1&
#70
b10001 !
b10001 *
1#
#72
0#
b10010 $
b10010 )
bx !
bx *
b10010 "
b10010 (
b10010 '
1%
1&
#74
b10010 !
b10010 *
1#
#76
0#
b10011 $
b10011 )
bx !
bx *
b10011 "
b10011 (
b10011 '
1%
1&
#78
b10011 !
b10011 *
1#
#80
0#
b10100 $
b10100 )
bx !
bx *
b10100 "
b10100 (
b10100 '
1%
1&
#82
b10100 !
b10100 *
1#
#84
0#
b10101 $
b10101 )
bx !
bx *
b10101 "
b10101 (
b10101 '
1%
1&
#86
b10101 !
b10101 *
1#
#88
0#
b10110 $
b10110 )
bx !
bx *
b10110 "
b10110 (
b10110 '
1%
1&
#90
b10110 !
b10110 *
1#
#92
0#
b10111 $
b10111 )
bx !
bx *
b10111 "
b10111 (
b10111 '
1%
1&
#94
b10111 !
b10111 *
1#
#96
0#
b11000 $
b11000 )
bx !
bx *
b11000 "
b11000 (
b11000 '
1%
1&
#98
b11000 !
b11000 *
1#
#100
0#
b11001 $
b11001 )
bx !
bx *
b11001 "
b11001 (
b11001 '
1%
1&
#102
b11001 !
b11001 *
1#
#104
0#
b11010 $
b11010 )
bx !
bx *
b11010 "
b11010 (
b11010 '
1%
1&
#106
b11010 !
b11010 *
1#
#108
0#
b11011 $
b11011 )
bx !
bx *
b11011 "
b11011 (
b11011 '
1%
1&
#110
b11011 !
b11011 *
1#
#112
0#
b11100 $
b11100 )
bx !
bx *
b11100 "
b11100 (
b11100 '
1%
1&
#114
b11100 !
b11100 *
1#
#116
0#
b11101 $
b11101 )
bx !
bx *
b11101 "
b11101 (
b11101 '
1%
1&
#118
b11101 !
b11101 *
1#
#120
0#
b11110 $
b11110 )
bx !
bx *
b11110 "
b11110 (
b11110 '
1%
1&
#122
b11110 !
b11110 *
1#
#124
0#
b11111 $
b11111 )
bx !
bx *
b11111 "
b11111 (
b11111 '
1%
1&
#126
b11111 !
b11111 *
1#
#128
0#
b100000 $
b100000 )
bx !
bx *
b100000 "
b100000 (
b100000 '
1%
1&
#130
b100000 !
b100000 *
1#
#132
0#
b100001 $
b100001 )
bx !
bx *
b100001 "
b100001 (
b100001 '
1%
1&
#134
b100001 !
b100001 *
1#
#136
0#
b100010 $
b100010 )
bx !
bx *
b100010 "
b100010 (
b100010 '
1%
1&
#138
b100010 !
b100010 *
1#
#140
0#
b100011 $
b100011 )
bx !
bx *
b100011 "
b100011 (
b100011 '
1%
1&
#142
b100011 !
b100011 *
1#
#144
0#
b100100 $
b100100 )
bx !
bx *
b100100 "
b100100 (
b100100 '
1%
1&
#146
b100100 !
b100100 *
1#
#148
0#
b100101 $
b100101 )
bx !
bx *
b100101 "
b100101 (
b100101 '
1%
1&
#150
b100101 !
b100101 *
1#
#152
0#
b100110 $
b100110 )
bx !
bx *
b100110 "
b100110 (
b100110 '
1%
1&
#154
b100110 !
b100110 *
1#
#156
0#
b100111 $
b100111 )
bx !
bx *
b100111 "
b100111 (
b100111 '
1%
1&
#158
b100111 !
b100111 *
1#
#160
0#
b101000 $
b101000 )
bx !
bx *
b101000 "
b101000 (
b101000 '
1%
1&
#162
b101000 !
b101000 *
1#
#164
0#
b101001 $
b101001 )
bx !
bx *
b101001 "
b101001 (
b101001 '
1%
1&
#166
b101001 !
b101001 *
1#
#168
0#
b101010 $
b101010 )
bx !
bx *
b101010 "
b101010 (
b101010 '
1%
1&
#170
b101010 !
b101010 *
1#
#172
0#
b101011 $
b101011 )
bx !
bx *
b101011 "
b101011 (
b101011 '
1%
1&
#174
b101011 !
b101011 *
1#
#176
0#
b101100 $
b101100 )
bx !
bx *
b101100 "
b101100 (
b101100 '
1%
1&
#178
b101100 !
b101100 *
1#
#180
0#
b101101 $
b101101 )
bx !
bx *
b101101 "
b101101 (
b101101 '
1%
1&
#182
b101101 !
b101101 *
1#
#184
0#
b101110 $
b101110 )
bx !
bx *
b101110 "
b101110 (
b101110 '
1%
1&
#186
b101110 !
b101110 *
1#
#188
0#
b101111 $
b101111 )
bx !
bx *
b101111 "
b101111 (
b101111 '
1%
1&
#190
b101111 !
b101111 *
1#
#192
0#
b110000 $
b110000 )
bx !
bx *
b110000 "
b110000 (
b110000 '
1%
1&
#194
b110000 !
b110000 *
1#
#196
0#
b110001 $
b110001 )
bx !
bx *
b110001 "
b110001 (
b110001 '
1%
1&
#198
b110001 !
b110001 *
1#
#200
0#
b110010 $
b110010 )
bx !
bx *
b110010 "
b110010 (
b110010 '
1%
1&
#202
b110010 !
b110010 *
1#
#204
0#
b110011 $
b110011 )
bx !
bx *
b110011 "
b110011 (
b110011 '
1%
1&
#206
b110011 !
b110011 *
1#
#208
0#
b110100 $
b110100 )
bx !
bx *
b110100 "
b110100 (
b110100 '
1%
1&
#210
b110100 !
b110100 *
1#
#212
0#
b110101 $
b110101 )
bx !
bx *
b110101 "
b110101 (
b110101 '
1%
1&
#214
b110101 !
b110101 *
1#
#216
0#
b110110 $
b110110 )
bx !
bx *
b110110 "
b110110 (
b110110 '
1%
1&
#218
b110110 !
b110110 *
1#
#220
0#
b110111 $
b110111 )
bx !
bx *
b110111 "
b110111 (
b110111 '
1%
1&
#222
b110111 !
b110111 *
1#
#224
0#
b111000 $
b111000 )
bx !
bx *
b111000 "
b111000 (
b111000 '
1%
1&
#226
b111000 !
b111000 *
1#
#228
0#
b111001 $
b111001 )
bx !
bx *
b111001 "
b111001 (
b111001 '
1%
1&
#230
b111001 !
b111001 *
1#
#232
0#
b111010 $
b111010 )
bx !
bx *
b111010 "
b111010 (
b111010 '
1%
1&
#234
b111010 !
b111010 *
1#
#236
0#
b111011 $
b111011 )
bx !
bx *
b111011 "
b111011 (
b111011 '
1%
1&
#238
b111011 !
b111011 *
1#
#240
0#
b111100 $
b111100 )
bx !
bx *
b111100 "
b111100 (
b111100 '
1%
1&
#242
b111100 !
b111100 *
1#
#244
0#
b111101 $
b111101 )
bx !
bx *
b111101 "
b111101 (
b111101 '
1%
1&
#246
b111101 !
b111101 *
1#
#248
0#
b111110 $
b111110 )
bx !
bx *
b111110 "
b111110 (
b111110 '
1%
1&
#250
b111110 !
b111110 *
1#
#252
0#
b111111 $
b111111 )
bx !
bx *
b111111 "
b111111 (
b111111 '
1%
1&
#254
b111111 !
b111111 *
1#
#256
0#
b1000000 $
b1000000 )
bx !
bx *
b1000000 "
b1000000 (
b1000000 '
1%
1&
#258
b1000000 !
b1000000 *
1#
#260
0#
b1000001 $
b1000001 )
bx !
bx *
b1000001 "
b1000001 (
b1000001 '
1%
1&
#262
b1000001 !
b1000001 *
1#
#264
0#
b1000010 $
b1000010 )
bx !
bx *
b1000010 "
b1000010 (
b1000010 '
1%
1&
#266
b1000010 !
b1000010 *
1#
#268
0#
b1000011 $
b1000011 )
bx !
bx *
b1000011 "
b1000011 (
b1000011 '
1%
1&
#270
b1000011 !
b1000011 *
1#
#272
0#
b1000100 $
b1000100 )
bx !
bx *
b1000100 "
b1000100 (
b1000100 '
1%
1&
#274
b1000100 !
b1000100 *
1#
#276
0#
b1000101 $
b1000101 )
bx !
bx *
b1000101 "
b1000101 (
b1000101 '
1%
1&
#278
b1000101 !
b1000101 *
1#
#280
0#
b1000110 $
b1000110 )
bx !
bx *
b1000110 "
b1000110 (
b1000110 '
1%
1&
#282
b1000110 !
b1000110 *
1#
#284
0#
b1000111 $
b1000111 )
bx !
bx *
b1000111 "
b1000111 (
b1000111 '
1%
1&
#286
b1000111 !
b1000111 *
1#
#288
0#
b1001000 $
b1001000 )
bx !
bx *
b1001000 "
b1001000 (
b1001000 '
1%
1&
#290
b1001000 !
b1001000 *
1#
#292
0#
b1001001 $
b1001001 )
bx !
bx *
b1001001 "
b1001001 (
b1001001 '
1%
1&
#294
b1001001 !
b1001001 *
1#
#296
0#
b1001010 $
b1001010 )
bx !
bx *
b1001010 "
b1001010 (
b1001010 '
1%
1&
#298
b1001010 !
b1001010 *
1#
#300
0#
b1001011 $
b1001011 )
bx !
bx *
b1001011 "
b1001011 (
b1001011 '
1%
1&
#302
b1001011 !
b1001011 *
1#
#304
0#
b1001100 $
b1001100 )
bx !
bx *
b1001100 "
b1001100 (
b1001100 '
1%
1&
#306
b1001100 !
b1001100 *
1#
#308
0#
b1001101 $
b1001101 )
bx !
bx *
b1001101 "
b1001101 (
b1001101 '
1%
1&
#310
b1001101 !
b1001101 *
1#
#312
0#
b1001110 $
b1001110 )
bx !
bx *
b1001110 "
b1001110 (
b1001110 '
1%
1&
#314
b1001110 !
b1001110 *
1#
#316
0#
b1001111 $
b1001111 )
bx !
bx *
b1001111 "
b1001111 (
b1001111 '
1%
1&
#318
b1001111 !
b1001111 *
1#
#320
0#
b1010000 $
b1010000 )
bx !
bx *
b1010000 "
b1010000 (
b1010000 '
1%
1&
#322
b1010000 !
b1010000 *
1#
#324
0#
b1010001 $
b1010001 )
bx !
bx *
b1010001 "
b1010001 (
b1010001 '
1%
1&
#326
b1010001 !
b1010001 *
1#
#328
0#
b1010010 $
b1010010 )
bx !
bx *
b1010010 "
b1010010 (
b1010010 '
1%
1&
#330
b1010010 !
b1010010 *
1#
#332
0#
b1010011 $
b1010011 )
bx !
bx *
b1010011 "
b1010011 (
b1010011 '
1%
1&
#334
b1010011 !
b1010011 *
1#
#336
0#
b1010100 $
b1010100 )
bx !
bx *
b1010100 "
b1010100 (
b1010100 '
1%
1&
#338
b1010100 !
b1010100 *
1#
#340
0#
b1010101 $
b1010101 )
bx !
bx *
b1010101 "
b1010101 (
b1010101 '
1%
1&
#342
b1010101 !
b1010101 *
1#
#344
0#
b1010110 $
b1010110 )
bx !
bx *
b1010110 "
b1010110 (
b1010110 '
1%
1&
#346
b1010110 !
b1010110 *
1#
#348
0#
b1010111 $
b1010111 )
bx !
bx *
b1010111 "
b1010111 (
b1010111 '
1%
1&
#350
b1010111 !
b1010111 *
1#
#352
0#
b1011000 $
b1011000 )
bx !
bx *
b1011000 "
b1011000 (
b1011000 '
1%
1&
#354
b1011000 !
b1011000 *
1#
#356
0#
b1011001 $
b1011001 )
bx !
bx *
b1011001 "
b1011001 (
b1011001 '
1%
1&
#358
b1011001 !
b1011001 *
1#
#360
0#
b1011010 $
b1011010 )
bx !
bx *
b1011010 "
b1011010 (
b1011010 '
1%
1&
#362
b1011010 !
b1011010 *
1#
#364
0#
b1011011 $
b1011011 )
bx !
bx *
b1011011 "
b1011011 (
b1011011 '
1%
1&
#366
b1011011 !
b1011011 *
1#
#368
0#
b1011100 $
b1011100 )
bx !
bx *
b1011100 "
b1011100 (
b1011100 '
1%
1&
#370
b1011100 !
b1011100 *
1#
#372
0#
b1011101 $
b1011101 )
bx !
bx *
b1011101 "
b1011101 (
b1011101 '
1%
1&
#374
b1011101 !
b1011101 *
1#
#376
0#
b1011110 $
b1011110 )
bx !
bx *
b1011110 "
b1011110 (
b1011110 '
1%
1&
#378
b1011110 !
b1011110 *
1#
#380
0#
b1011111 $
b1011111 )
bx !
bx *
b1011111 "
b1011111 (
b1011111 '
1%
1&
#382
b1011111 !
b1011111 *
1#
#384
0#
b1100000 $
b1100000 )
bx !
bx *
b1100000 "
b1100000 (
b1100000 '
1%
1&
#386
b1100000 !
b1100000 *
1#
#388
0#
b1100001 $
b1100001 )
bx !
bx *
b1100001 "
b1100001 (
b1100001 '
1%
1&
#390
b1100001 !
b1100001 *
1#
#392
0#
b1100010 $
b1100010 )
bx !
bx *
b1100010 "
b1100010 (
b1100010 '
1%
1&
#394
b1100010 !
b1100010 *
1#
#396
0#
b1100011 $
b1100011 )
bx !
bx *
b1100011 "
b1100011 (
b1100011 '
1%
1&
#398
b1100011 !
b1100011 *
1#
#400
0#
b1100100 $
b1100100 )
bx !
bx *
b1100100 "
b1100100 (
b1100100 '
1%
1&
#402
b1100100 !
b1100100 *
1#
#404
0#
b1100101 $
b1100101 )
bx !
bx *
b1100101 "
b1100101 (
b1100101 '
1%
1&
#406
b1100101 !
b1100101 *
1#
#408
0#
b1100110 $
b1100110 )
bx !
bx *
b1100110 "
b1100110 (
b1100110 '
1%
1&
#410
b1100110 !
b1100110 *
1#
#412
0#
b1100111 $
b1100111 )
bx !
bx *
b1100111 "
b1100111 (
b1100111 '
1%
1&
#414
b1100111 !
b1100111 *
1#
#416
0#
b1101000 $
b1101000 )
bx !
bx *
b1101000 "
b1101000 (
b1101000 '
1%
1&
#418
b1101000 !
b1101000 *
1#
#420
0#
b1101001 $
b1101001 )
bx !
bx *
b1101001 "
b1101001 (
b1101001 '
1%
1&
#422
b1101001 !
b1101001 *
1#
#424
0#
b1101010 $
b1101010 )
bx !
bx *
b1101010 "
b1101010 (
b1101010 '
1%
1&
#426
b1101010 !
b1101010 *
1#
#428
0#
b1101011 $
b1101011 )
bx !
bx *
b1101011 "
b1101011 (
b1101011 '
1%
1&
#430
b1101011 !
b1101011 *
1#
#432
0#
b1101100 $
b1101100 )
bx !
bx *
b1101100 "
b1101100 (
b1101100 '
1%
1&
#434
b1101100 !
b1101100 *
1#
#436
0#
b1101101 $
b1101101 )
bx !
bx *
b1101101 "
b1101101 (
b1101101 '
1%
1&
#438
b1101101 !
b1101101 *
1#
#440
0#
b1101110 $
b1101110 )
bx !
bx *
b1101110 "
b1101110 (
b1101110 '
1%
1&
#442
b1101110 !
b1101110 *
1#
#444
0#
b1101111 $
b1101111 )
bx !
bx *
b1101111 "
b1101111 (
b1101111 '
1%
1&
#446
b1101111 !
b1101111 *
1#
#448
0#
b1110000 $
b1110000 )
bx !
bx *
b1110000 "
b1110000 (
b1110000 '
1%
1&
#450
b1110000 !
b1110000 *
1#
#452
0#
b1110001 $
b1110001 )
bx !
bx *
b1110001 "
b1110001 (
b1110001 '
1%
1&
#454
b1110001 !
b1110001 *
1#
#456
0#
b1110010 $
b1110010 )
bx !
bx *
b1110010 "
b1110010 (
b1110010 '
1%
1&
#458
b1110010 !
b1110010 *
1#
#460
0#
b1110011 $
b1110011 )
bx !
bx *
b1110011 "
b1110011 (
b1110011 '
1%
1&
#462
b1110011 !
b1110011 *
1#
#464
0#
b1110100 $
b1110100 )
bx !
bx *
b1110100 "
b1110100 (
b1110100 '
1%
1&
#466
b1110100 !
b1110100 *
1#
#468
0#
b1110101 $
b1110101 )
bx !
bx *
b1110101 "
b1110101 (
b1110101 '
1%
1&
#470
b1110101 !
b1110101 *
1#
#472
0#
b1110110 $
b1110110 )
bx !
bx *
b1110110 "
b1110110 (
b1110110 '
1%
1&
#474
b1110110 !
b1110110 *
1#
#476
0#
b1110111 $
b1110111 )
bx !
bx *
b1110111 "
b1110111 (
b1110111 '
1%
1&
#478
b1110111 !
b1110111 *
1#
#480
0#
b1111000 $
b1111000 )
bx !
bx *
b1111000 "
b1111000 (
b1111000 '
1%
1&
#482
b1111000 !
b1111000 *
1#
#484
0#
b1111001 $
b1111001 )
bx !
bx *
b1111001 "
b1111001 (
b1111001 '
1%
1&
#486
b1111001 !
b1111001 *
1#
#488
0#
b1111010 $
b1111010 )
bx !
bx *
b1111010 "
b1111010 (
b1111010 '
1%
1&
#490
b1111010 !
b1111010 *
1#
#492
0#
b1111011 $
b1111011 )
bx !
bx *
b1111011 "
b1111011 (
b1111011 '
1%
1&
#494
b1111011 !
b1111011 *
1#
#496
0#
b1111100 $
b1111100 )
bx !
bx *
b1111100 "
b1111100 (
b1111100 '
1%
1&
#498
b1111100 !
b1111100 *
1#
#500
0#
b1111101 $
b1111101 )
bx !
bx *
b1111101 "
b1111101 (
b1111101 '
1%
1&
#502
b1111101 !
b1111101 *
1#
#504
0#
b1111110 $
b1111110 )
bx !
bx *
b1111110 "
b1111110 (
b1111110 '
1%
1&
#506
b1111110 !
b1111110 *
1#
#508
0#
b1111111 $
b1111111 )
bx !
bx *
b1111111 "
b1111111 (
b1111111 '
1%
1&
#510
b1111111 !
b1111111 *
1#
#512
0#
b10000000 $
b10000000 )
bx !
bx *
b10000000 "
b10000000 (
b10000000 '
1%
1&
#514
b10000000 !
b10000000 *
1#
#516
0#
b10000001 $
b10000001 )
bx !
bx *
b10000001 "
b10000001 (
b10000001 '
1%
1&
#518
b10000001 !
b10000001 *
1#
#520
0#
b10000010 $
b10000010 )
bx !
bx *
b10000010 "
b10000010 (
b10000010 '
1%
1&
#522
b10000010 !
b10000010 *
1#
#524
0#
b10000011 $
b10000011 )
bx !
bx *
b10000011 "
b10000011 (
b10000011 '
1%
1&
#526
b10000011 !
b10000011 *
1#
#528
0#
b10000100 $
b10000100 )
bx !
bx *
b10000100 "
b10000100 (
b10000100 '
1%
1&
#530
b10000100 !
b10000100 *
1#
#532
0#
b10000101 $
b10000101 )
bx !
bx *
b10000101 "
b10000101 (
b10000101 '
1%
1&
#534
b10000101 !
b10000101 *
1#
#536
0#
b10000110 $
b10000110 )
bx !
bx *
b10000110 "
b10000110 (
b10000110 '
1%
1&
#538
b10000110 !
b10000110 *
1#
#540
0#
b10000111 $
b10000111 )
bx !
bx *
b10000111 "
b10000111 (
b10000111 '
1%
1&
#542
b10000111 !
b10000111 *
1#
#544
0#
b10001000 $
b10001000 )
bx !
bx *
b10001000 "
b10001000 (
b10001000 '
1%
1&
#546
b10001000 !
b10001000 *
1#
#548
0#
b10001001 $
b10001001 )
bx !
bx *
b10001001 "
b10001001 (
b10001001 '
1%
1&
#550
b10001001 !
b10001001 *
1#
#552
0#
b10001010 $
b10001010 )
bx !
bx *
b10001010 "
b10001010 (
b10001010 '
1%
1&
#554
b10001010 !
b10001010 *
1#
#556
0#
b10001011 $
b10001011 )
bx !
bx *
b10001011 "
b10001011 (
b10001011 '
1%
1&
#558
b10001011 !
b10001011 *
1#
#560
0#
b10001100 $
b10001100 )
bx !
bx *
b10001100 "
b10001100 (
b10001100 '
1%
1&
#562
b10001100 !
b10001100 *
1#
#564
0#
b10001101 $
b10001101 )
bx !
bx *
b10001101 "
b10001101 (
b10001101 '
1%
1&
#566
b10001101 !
b10001101 *
1#
#568
0#
b10001110 $
b10001110 )
bx !
bx *
b10001110 "
b10001110 (
b10001110 '
1%
1&
#570
b10001110 !
b10001110 *
1#
#572
0#
b10001111 $
b10001111 )
bx !
bx *
b10001111 "
b10001111 (
b10001111 '
1%
1&
#574
b10001111 !
b10001111 *
1#
#576
0#
b10010000 $
b10010000 )
bx !
bx *
b10010000 "
b10010000 (
b10010000 '
1%
1&
#578
b10010000 !
b10010000 *
1#
#580
0#
b10010001 $
b10010001 )
bx !
bx *
b10010001 "
b10010001 (
b10010001 '
1%
1&
#582
b10010001 !
b10010001 *
1#
#584
0#
b10010010 $
b10010010 )
bx !
bx *
b10010010 "
b10010010 (
b10010010 '
1%
1&
#586
b10010010 !
b10010010 *
1#
#588
0#
b10010011 $
b10010011 )
bx !
bx *
b10010011 "
b10010011 (
b10010011 '
1%
1&
#590
b10010011 !
b10010011 *
1#
#592
0#
b10010100 $
b10010100 )
bx !
bx *
b10010100 "
b10010100 (
b10010100 '
1%
1&
#594
b10010100 !
b10010100 *
1#
#596
0#
b10010101 $
b10010101 )
bx !
bx *
b10010101 "
b10010101 (
b10010101 '
1%
1&
#598
b10010101 !
b10010101 *
1#
#600
0#
b10010110 $
b10010110 )
bx !
bx *
b10010110 "
b10010110 (
b10010110 '
1%
1&
#602
b10010110 !
b10010110 *
1#
#604
0#
b10010111 $
b10010111 )
bx !
bx *
b10010111 "
b10010111 (
b10010111 '
1%
1&
#606
b10010111 !
b10010111 *
1#
#608
0#
b10011000 $
b10011000 )
bx !
bx *
b10011000 "
b10011000 (
b10011000 '
1%
1&
#610
b10011000 !
b10011000 *
1#
#612
0#
b10011001 $
b10011001 )
bx !
bx *
b10011001 "
b10011001 (
b10011001 '
1%
1&
#614
b10011001 !
b10011001 *
1#
#616
0#
b10011010 $
b10011010 )
bx !
bx *
b10011010 "
b10011010 (
b10011010 '
1%
1&
#618
b10011010 !
b10011010 *
1#
#620
0#
b10011011 $
b10011011 )
bx !
bx *
b10011011 "
b10011011 (
b10011011 '
1%
1&
#622
b10011011 !
b10011011 *
1#
#624
0#
b10011100 $
b10011100 )
bx !
bx *
b10011100 "
b10011100 (
b10011100 '
1%
1&
#626
b10011100 !
b10011100 *
1#
#628
0#
b10011101 $
b10011101 )
bx !
bx *
b10011101 "
b10011101 (
b10011101 '
1%
1&
#630
b10011101 !
b10011101 *
1#
#632
0#
b10011110 $
b10011110 )
bx !
bx *
b10011110 "
b10011110 (
b10011110 '
1%
1&
#634
b10011110 !
b10011110 *
1#
#636
0#
b10011111 $
b10011111 )
bx !
bx *
b10011111 "
b10011111 (
b10011111 '
1%
1&
#638
b10011111 !
b10011111 *
1#
#640
0#
b10100000 $
b10100000 )
bx !
bx *
b10100000 "
b10100000 (
b10100000 '
1%
1&
#642
b10100000 !
b10100000 *
1#
#644
0#
b10100001 $
b10100001 )
bx !
bx *
b10100001 "
b10100001 (
b10100001 '
1%
1&
#646
b10100001 !
b10100001 *
1#
#648
0#
b10100010 $
b10100010 )
bx !
bx *
b10100010 "
b10100010 (
b10100010 '
1%
1&
#650
b10100010 !
b10100010 *
1#
#652
0#
b10100011 $
b10100011 )
bx !
bx *
b10100011 "
b10100011 (
b10100011 '
1%
1&
#654
b10100011 !
b10100011 *
1#
#656
0#
b10100100 $
b10100100 )
bx !
bx *
b10100100 "
b10100100 (
b10100100 '
1%
1&
#658
b10100100 !
b10100100 *
1#
#660
0#
b10100101 $
b10100101 )
bx !
bx *
b10100101 "
b10100101 (
b10100101 '
1%
1&
#662
b10100101 !
b10100101 *
1#
#664
0#
b10100110 $
b10100110 )
bx !
bx *
b10100110 "
b10100110 (
b10100110 '
1%
1&
#666
b10100110 !
b10100110 *
1#
#668
0#
b10100111 $
b10100111 )
bx !
bx *
b10100111 "
b10100111 (
b10100111 '
1%
1&
#670
b10100111 !
b10100111 *
1#
#672
0#
b10101000 $
b10101000 )
bx !
bx *
b10101000 "
b10101000 (
b10101000 '
1%
1&
#674
b10101000 !
b10101000 *
1#
#676
0#
b10101001 $
b10101001 )
bx !
bx *
b10101001 "
b10101001 (
b10101001 '
1%
1&
#678
b10101001 !
b10101001 *
1#
#680
0#
b10101010 $
b10101010 )
bx !
bx *
b10101010 "
b10101010 (
b10101010 '
1%
1&
#682
b10101010 !
b10101010 *
1#
#684
0#
b10101011 $
b10101011 )
bx !
bx *
b10101011 "
b10101011 (
b10101011 '
1%
1&
#686
b10101011 !
b10101011 *
1#
#688
0#
b10101100 $
b10101100 )
bx !
bx *
b10101100 "
b10101100 (
b10101100 '
1%
1&
#690
b10101100 !
b10101100 *
1#
#692
0#
b10101101 $
b10101101 )
bx !
bx *
b10101101 "
b10101101 (
b10101101 '
1%
1&
#694
b10101101 !
b10101101 *
1#
#696
0#
b10101110 $
b10101110 )
bx !
bx *
b10101110 "
b10101110 (
b10101110 '
1%
1&
#698
b10101110 !
b10101110 *
1#
#700
0#
b10101111 $
b10101111 )
bx !
bx *
b10101111 "
b10101111 (
b10101111 '
1%
1&
#702
b10101111 !
b10101111 *
1#
#704
0#
b10110000 $
b10110000 )
bx !
bx *
b10110000 "
b10110000 (
b10110000 '
1%
1&
#706
b10110000 !
b10110000 *
1#
#708
0#
b10110001 $
b10110001 )
bx !
bx *
b10110001 "
b10110001 (
b10110001 '
1%
1&
#710
b10110001 !
b10110001 *
1#
#712
0#
b10110010 $
b10110010 )
bx !
bx *
b10110010 "
b10110010 (
b10110010 '
1%
1&
#714
b10110010 !
b10110010 *
1#
#716
0#
b10110011 $
b10110011 )
bx !
bx *
b10110011 "
b10110011 (
b10110011 '
1%
1&
#718
b10110011 !
b10110011 *
1#
#720
0#
b10110100 $
b10110100 )
bx !
bx *
b10110100 "
b10110100 (
b10110100 '
1%
1&
#722
b10110100 !
b10110100 *
1#
#724
0#
b10110101 $
b10110101 )
bx !
bx *
b10110101 "
b10110101 (
b10110101 '
1%
1&
#726
b10110101 !
b10110101 *
1#
#728
0#
b10110110 $
b10110110 )
bx !
bx *
b10110110 "
b10110110 (
b10110110 '
1%
1&
#730
b10110110 !
b10110110 *
1#
#732
0#
b10110111 $
b10110111 )
bx !
bx *
b10110111 "
b10110111 (
b10110111 '
1%
1&
#734
b10110111 !
b10110111 *
1#
#736
0#
b10111000 $
b10111000 )
bx !
bx *
b10111000 "
b10111000 (
b10111000 '
1%
1&
#738
b10111000 !
b10111000 *
1#
#740
0#
b10111001 $
b10111001 )
bx !
bx *
b10111001 "
b10111001 (
b10111001 '
1%
1&
#742
b10111001 !
b10111001 *
1#
#744
0#
b10111010 $
b10111010 )
bx !
bx *
b10111010 "
b10111010 (
b10111010 '
1%
1&
#746
b10111010 !
b10111010 *
1#
#748
0#
b10111011 $
b10111011 )
bx !
bx *
b10111011 "
b10111011 (
b10111011 '
1%
1&
#750
b10111011 !
b10111011 *
1#
#752
0#
b10111100 $
b10111100 )
bx !
bx *
b10111100 "
b10111100 (
b10111100 '
1%
1&
#754
b10111100 !
b10111100 *
1#
#756
0#
b10111101 $
b10111101 )
bx !
bx *
b10111101 "
b10111101 (
b10111101 '
1%
1&
#758
b10111101 !
b10111101 *
1#
#760
0#
b10111110 $
b10111110 )
bx !
bx *
b10111110 "
b10111110 (
b10111110 '
1%
1&
#762
b10111110 !
b10111110 *
1#
#764
0#
b10111111 $
b10111111 )
bx !
bx *
b10111111 "
b10111111 (
b10111111 '
1%
1&
#766
b10111111 !
b10111111 *
1#
#768
0#
b11000000 $
b11000000 )
bx !
bx *
b11000000 "
b11000000 (
b11000000 '
1%
1&
#770
b11000000 !
b11000000 *
1#
#772
0#
b11000001 $
b11000001 )
bx !
bx *
b11000001 "
b11000001 (
b11000001 '
1%
1&
