sequence_detector/sequence_detector.v
module sequence_detector(input x,clk,reset, output reg z);
	parameter S0=0, S1=1, S2=2, S3=3;
	reg [0:1] PS,NS;
	
	always @(posedge clk or posedge reset) begin
		if(reset) PS<= S0;
		else PS<=NS;
	end
	
	always @(PS,x) begin
		case(PS)
			S0: begin
				z= 0;
				NS = x ? S1 : S0;
				end
			
			S1: begin
				z=0;
				NS =x ? S1: S2;
				end
			
			S2: begin
				z=0;
				NS = x ? S3 : S0;
				end
			
			S3: begin
				z= x ? 0 : 1;
				NS= x ? S1 : S2;
				end
		endcase
	end
endmodule

sequence_detector/sequence_detector_test.v
module sequence_detector_test;
reg x,clk,reset;
wire z;



sequence_detector SEQ (.x(x),.clk(clk),.reset(reset),.z(z));
initial begin
	$dumpfile("sequence_detector.vcd");
	$dumpvars(0,sequence_detector_test);
	//$monitor("input=%b , output=%b",x,z);
	clk=0; reset=1;
	#15 reset=0;
end
always #5 clk=~clk;

initial begin
	#10 x=0; #10 x=0; #10 x=1; #10 x=1; 
	#10 x=0; #10 x=1; #10 x=0; #10 x=1;
	#10 x=0; #10 x=1; #10 x=1; #10 x=0;
	#10 $finish;
end
endmodule

sequence_detector/sequence_detector.vcd
$date
	Fri Nov 27 00:53:06 2020
$end
$version
	Icarus Verilog
$end
$timescale
	1s
$end
$scope module sequence_detector_test $end
$var wire 1 ! z $end
$var reg 1 " clk $end
$var reg 1 # reset $end
$var reg 1 $ x $end
$scope module SEQ $end
$var wire 1 " clk $end
$var wire 1 # reset $end
$var wire 1 $ x $end
$var reg 2 % NS [0:1] $end
$var reg 2 & PS [0:1] $end
$var reg 1 ! z $end
$upscope $end
$upscope $end
$enddefinitions $end
#0
$dumpvars
b0 &
b0x %
x$
1#
0"
0!
$end
#5
1"
#10
b0 %
0"
0$
#15
1"
0#
#20
0"
#25
1"
#30
b1 %
0"
1$
#35
b1 &
1"
#40
0"
#45
1"
#50
b10 %
0"
0$
#55
b0 %
b10 &
1"
#60
b11 %
0"
1$
#65
b1 %
b11 &
1"
#70
b10 %
1!
0"
0$
#75
b0 %
0!
b10 &
1"
#80
b11 %
0"
1$
#85
b1 %
b11 &
1"
#90
b10 %
1!
0"
0$
#95
b0 %
0!
b10 &
1"
#100
b11 %
0"
1$
#105
b1 %
b11 &
1"
#110
0"
#115
b1 &
1"
#120
b10 %
0"
0$
#125
b0 %
b10 &
1"
